<?xml version="1.0" encoding="UTF-8"?>
<monster name="Ho-oh" nameDescription="Fantastic] Ho-oh" race="undead" experience="90000" speed="800" manacost="590">
  <health now="140000" max="140000"/>
  <look type="417" head="20" body="30" legs="40" feet="50" corpse="2832"/>

  <targetchange interval="1000" chance="1000"/>
  <strategy attack="100" defense="100"/>
  <flags>
    <flag summonable="1"/>
    <flag attackable="1"/>
    <flag hostile="1"/>
    <flag illusionable="1"/>
    <flag convinceable="1"/>
    <flag pushable="0"/>
    <flag canpushitems="1"/>
    <flag canpushcreatures="1"/>
    <flag targetdistance="1"/>
    <flag staticattack="90"/>
    <flag runonhealth="0"/>
  </flags>
   <attacks>
    <attack name="scratch" interval="1000" chance="50" min="-1520" max="-2285">
    </attack>
    <attack name="dragon rage" interval="1500" chance="90" min="-1220" max="-2290">
    </attack>
    <attack name="ember" interval="3500" chance="90" min="-15000" max="-12500">
    </attack>
    <attack name="flamethrower" interval="2000" chance="100" min="-9500" max="-11800">
    </attack>
    <attack name="fire blast" interval="3000" chance="90" min="-24500" max="-28000">
    </attack>
    <attack name="fire spin" interval="3500" chance="100" min="-10000" max="-17000">
    </attack>
    <attack name="magma storm" interval="2000" chance="90" min="-30000" max="-47000">
    </attack>
  </attacks>
  <defenses armor="1" defense="1">
    <defense name="Intense Healing" interval="3000" chance="100" min="6000" max="7000">
    </defense>
  </defenses>
  <elements>
		<element firePercent="50"/>
		<element drownPercent="-100"/>
		<element grassPercent="50"/>
		<element icePercent="50"/>
		<element groundPercent="-100"/>
		<element bugPercent="50"/>
		<element rockPercent="-100"/>
  </elements>
	<voices interval="5000" chance="10">
		<voice sentence="Hooooo!"/>
		<voice sentence="Ho-Oh!"/>
	</voices>
	<loot>
		<item id="5894" countmax="15" chance="15000"/><!-- Sell Item -->
		<item id="5890" countmax="5" chance="7000"/><!-- Sell Item -->
		<item id="5910" countmax="2" chance="4500"/><!-- Sell Item -->
		<item id="5907" chance="300"/><!-- Stone -->
	</loot>
</monster>
